zuul_sphinx/__init__.py
zuul_sphinx/version.py
zuul_sphinx/zuul.py
zuul_sphinx-0.7.0.dist-info/AUTHORS
zuul_sphinx-0.7.0.dist-info/LICENSE
zuul_sphinx-0.7.0.dist-info/METADATA
zuul_sphinx-0.7.0.dist-info/WHEEL
zuul_sphinx-0.7.0.dist-info/pbr.json
zuul_sphinx-0.7.0.dist-info/top_level.txt
zuul_sphinx-0.7.0.dist-info/RECORD
