Metadata-Version: 2.1
Name: zuul-sphinx
Version: 0.7.0
Summary: A Sphinx extension for documenting Zuul jobs
Home-page: https://docs.openstack.org/infra/zuul-sphinx/
Author: OpenStack Infrastructure Team
Author-email: openstack-infra@lists.openstack.org
License: UNKNOWN
Platform: UNKNOWN
Classifier: Environment :: OpenStack
Classifier: Intended Audience :: Information Technology
Classifier: Intended Audience :: System Administrators
Classifier: License :: OSI Approved :: Apache Software License
Classifier: Operating System :: POSIX :: Linux
Classifier: Programming Language :: Python
Classifier: Programming Language :: Python :: 3
Classifier: Programming Language :: Python :: 3.5
License-File: LICENSE
Requires-Dist: pbr (>=1.1.0)
Requires-Dist: pyyaml
Requires-Dist: sphinx (>=1.5.1)
